setup.py
pysnafu.egg-info/PKG-INFO
pysnafu.egg-info/SOURCES.txt
pysnafu.egg-info/dependency_links.txt
pysnafu.egg-info/not-zip-safe
pysnafu.egg-info/requires.txt
pysnafu.egg-info/top_level.txt
snafu/__init__.py
snafu/_version.py
snafu/clustering.py
snafu/core.py
snafu/frequency.py
snafu/generate_graphs.py
snafu/generate_lists.py
snafu/gui.py
snafu/helper.py
snafu/io.py
snafu/irts.py
snafu/netstats.py
snafu/pci.py
snafu/search.py
snafu/structs.py
snafu/triadic.py
snafu/word_properties.py